acronym_expander/__init__.py
acronym_expander/__main__.py
acronym_expander-0.1.1.dist-info/licenses/LICENSE
acronym_expander-0.1.1.dist-info/METADATA
acronym_expander-0.1.1.dist-info/WHEEL
acronym_expander-0.1.1.dist-info/entry_points.txt
acronym_expander-0.1.1.dist-info/top_level.txt
acronym_expander-0.1.1.dist-info/RECORD
