Metadata-Version: 2.4
Name: acronym-expander
Version: 0.1.1
Summary: Lightweight utility to expand common acronyms and abbreviations into full forms.
Author-email: Maanasvee Khetan <maanasveekhetan66@gmail.com>
License: MIT
Keywords: acronym,expand,nlp,text
Classifier: Programming Language :: Python :: 3
Classifier: License :: OSI Approved :: MIT License
Classifier: Operating System :: OS Independent
Requires-Python: >=3.6
License-File: LICENSE
Dynamic: license-file
Dynamic: requires-python
